libname/__init__.py
libname/linkslotgacor.py
link_slot_gacor-0.0.2.dist-info/METADATA
link_slot_gacor-0.0.2.dist-info/WHEEL
link_slot_gacor-0.0.2.dist-info/top_level.txt
link_slot_gacor-0.0.2.dist-info/RECORD
