Metadata-Version: 2.1
Name: link-slot-gacor
Version: 0.0.2
Summary: Link Slot Gacor
Home-page: UNKNOWN
Author: HIGGSGO
Author-email: <higgsgo@bonanzabon.click>
License: UNKNOWN
Keywords: higgsgo,link slot gacor,slot gacor,slot online,slot gacor ternama,judi online,togel online,agen slot online,bandar slot online,judi slot online,slot online terbaik,slot online terpercaya
Platform: UNKNOWN
Classifier: Development Status :: 1 - Planning
Classifier: Intended Audience :: Developers
Classifier: Programming Language :: Python :: 3
Classifier: Operating System :: Unix
Classifier: Operating System :: MacOS :: MacOS X
Classifier: Operating System :: Microsoft :: Windows
